<?xml version="1.0" encoding="utf-8" ?>
<Patch>
	<Operation Class="PatchOperationSequence">
		<success>Always</success>
		<operations>
			<li Class="CombatExtended.PatchOperationFindMod">
				<modName>AnimalCollabProj</modName>
			</li>
	
			<li Class="PatchOperationAddModExtension">
				<xpath>*/ThingDef[defName="ACPDirewolf"]</xpath>
				<value>
				<li Class="CombatExtended.RacePropertiesExtensionCE">
					<bodyShape>Quadruped</bodyShape>
				</li>
				</value>
			</li>
						
			<li Class="PatchOperationAdd">
				<xpath>*/ThingDef[defName="ACPDirewolf"]/statBases</xpath>
				<value>
				<MeleeDodgeChance>0.11</MeleeDodgeChance>
				<MeleeCritChance>0.6</MeleeCritChance>
				</value>
			</li>
			
			<li Class="PatchOperationReplace">
				<xpath>*/ThingDef[defName="ACPDirewolf"]/tools</xpath>
				<value>
					<tools>
						<li Class="CombatExtended.ToolCE">
							<label>left claw</label>
							<capacities><li>Slash</li></capacities>
							<power>11</power>
							<cooldownTime>1.5</cooldownTime>
							<linkedBodyPartsGroup>FrontLeftPaw</linkedBodyPartsGroup>
							<surpriseAttack>
								<extraMeleeDamages>
									<li>
										<def>Stun</def>
										<amount>20</amount>
									</li>
								</extraMeleeDamages>
							</surpriseAttack>
							<armorPenetration>0.3</armorPenetration>
						</li>
						<li Class="CombatExtended.ToolCE">
							<label>right claw</label>
							<capacities><li>Slash</li></capacities>
							<power>11</power>
							<cooldownTime>1.5</cooldownTime>
							<linkedBodyPartsGroup>FrontRightPaw</linkedBodyPartsGroup>
							<surpriseAttack>
								<extraMeleeDamages>
									<li>
										<def>Stun</def>
										<amount>20</amount>
									</li>
								</extraMeleeDamages>
							</surpriseAttack>
							<armorPenetration>0.3</armorPenetration>
						</li>
						<li Class="CombatExtended.ToolCE">
							<capacities><li>Bite</li></capacities>
							<power>13</power>
							<cooldownTime>2.0</cooldownTime>
							<linkedBodyPartsGroup>Teeth</linkedBodyPartsGroup>
							<surpriseAttack>
								<extraMeleeDamages>
									<li>
										<def>Stun</def>
										<amount>20</amount>
									</li>
								</extraMeleeDamages>
							</surpriseAttack>
							<armorPenetration>1.0</armorPenetration>
						</li>
					</tools>
				</value>
			</li>
			
			<li Class="PatchOperationAddModExtension">
				<xpath>*/ThingDef[defName="ACPBlackwolf"]</xpath>
				<value>
				<li Class="CombatExtended.RacePropertiesExtensionCE">
					<bodyShape>Quadruped</bodyShape>
				</li>
				</value>
			</li>
						
			<li Class="PatchOperationAdd">
				<xpath>*/ThingDef[defName="ACPBlackwolf"]/statBases</xpath>
				<value>
				<MeleeDodgeChance>0.10</MeleeDodgeChance>
				<MeleeCritChance>0.6</MeleeCritChance>
				</value>
			</li>
			
			<li Class="PatchOperationReplace">
				<xpath>*/ThingDef[defName="ACPBlackwolf"]/tools</xpath>
				<value>
					<tools>
						<li Class="CombatExtended.ToolCE">
							<label>left claw</label>
							<capacities><li>Slash</li></capacities>
							<power>14</power>
							<cooldownTime>1.5</cooldownTime>
							<linkedBodyPartsGroup>FrontLeftPaw</linkedBodyPartsGroup>
							<surpriseAttack>
								<extraMeleeDamages>
									<li>
										<def>Stun</def>
										<amount>20</amount>
									</li>
								</extraMeleeDamages>
							</surpriseAttack>
							<armorPenetration>0.35</armorPenetration>
						</li>
						<li Class="CombatExtended.ToolCE">
							<label>right claw</label>
							<capacities><li>Slash</li></capacities>
							<power>14</power>
							<cooldownTime>1.5</cooldownTime>
							<linkedBodyPartsGroup>FrontRightPaw</linkedBodyPartsGroup>
							<surpriseAttack>
								<extraMeleeDamages>
									<li>
										<def>Stun</def>
										<amount>20</amount>
									</li>
								</extraMeleeDamages>
							</surpriseAttack>
							<armorPenetration>0.35</armorPenetration>
						</li>
						<li Class="CombatExtended.ToolCE">
							<capacities><li>Bite</li></capacities>
							<power>16</power>
							<cooldownTime>2.0</cooldownTime>
							<linkedBodyPartsGroup>Teeth</linkedBodyPartsGroup>
							<surpriseAttack>
								<extraMeleeDamages>
									<li>
										<def>Stun</def>
										<amount>20</amount>
									</li>
								</extraMeleeDamages>
							</surpriseAttack>
							<armorPenetration>1.2</armorPenetration>
						</li>
					</tools>
				</value>
			</li>
			
			<li Class="PatchOperationAddModExtension">
				<xpath>*/ThingDef[defName="ACPSpiritwolf"]</xpath>
				<value>
				<li Class="CombatExtended.RacePropertiesExtensionCE">
					<bodyShape>Quadruped</bodyShape>
				</li>
				</value>
			</li>
						
			<li Class="PatchOperationAdd">
				<xpath>*/ThingDef[defName="ACPSpiritwolf"]/statBases</xpath>
				<value>
				<MeleeDodgeChance>0.08</MeleeDodgeChance>
				<MeleeCritChance>0.8</MeleeCritChance>
				</value>
			</li>
			
			<li Class="PatchOperationReplace">
				<xpath>*/ThingDef[defName="ACPSpiritwolf"]/tools</xpath>
				<value>
					<tools>
						<li Class="CombatExtended.ToolCE">
							<label>left claw</label>
							<capacities><li>Slash</li></capacities>
							<power>16</power>
							<cooldownTime>1.5</cooldownTime>
							<linkedBodyPartsGroup>FrontLeftPaw</linkedBodyPartsGroup>
							<surpriseAttack>
								<extraMeleeDamages>
									<li>
										<def>Stun</def>
										<amount>20</amount>
									</li>
								</extraMeleeDamages>
							</surpriseAttack>
							<armorPenetration>0.45</armorPenetration>
						</li>
						<li Class="CombatExtended.ToolCE">
							<label>right claw</label>
							<capacities><li>Slash</li></capacities>
							<power>16</power>
							<cooldownTime>1.5</cooldownTime>
							<linkedBodyPartsGroup>FrontRightPaw</linkedBodyPartsGroup>
							<surpriseAttack>
								<extraMeleeDamages>
									<li>
										<def>Stun</def>
										<amount>20</amount>
									</li>
								</extraMeleeDamages>
							</surpriseAttack>
							<armorPenetration>0.45</armorPenetration>
						</li>
						<li Class="CombatExtended.ToolCE">
							<capacities><li>Bite</li></capacities>
							<power>19</power>
							<cooldownTime>2.0</cooldownTime>
							<linkedBodyPartsGroup>Teeth</linkedBodyPartsGroup>
							<surpriseAttack>
								<extraMeleeDamages>
									<li>
										<def>Stun</def>
										<amount>24</amount>
									</li>
								</extraMeleeDamages>
							</surpriseAttack>
							<armorPenetration>1.4</armorPenetration>
						</li>
					</tools>
				</value>
			</li>
			
			<li Class="PatchOperationAddModExtension">
				<xpath>*/ThingDef[defName="ACPSpiritwolfFF"]</xpath>
				<value>
				<li Class="CombatExtended.RacePropertiesExtensionCE">
					<bodyShape>Quadruped</bodyShape>
				</li>
				</value>
			</li>
						
			<li Class="PatchOperationAdd">
				<xpath>*/ThingDef[defName="ACPSpiritwolfFF"]/statBases</xpath>
				<value>
				<MeleeDodgeChance>0.08</MeleeDodgeChance>
				<MeleeCritChance>0.8</MeleeCritChance>
				</value>
			</li>
			
			<li Class="PatchOperationReplace">
				<xpath>*/ThingDef[defName="ACPSpiritwolfFF"]/tools</xpath>
				<value>
					<tools>
						<li Class="CombatExtended.ToolCE">
							<label>left claw</label>
							<capacities><li>Slash</li></capacities>
							<power>16</power>
							<cooldownTime>1.5</cooldownTime>
							<linkedBodyPartsGroup>FrontLeftPaw</linkedBodyPartsGroup>
							<surpriseAttack>
								<extraMeleeDamages>
									<li>
										<def>Stun</def>
										<amount>20</amount>
									</li>
								</extraMeleeDamages>
							</surpriseAttack>
							<armorPenetration>0.45</armorPenetration>
						</li>
						<li Class="CombatExtended.ToolCE">
							<label>right claw</label>
							<capacities><li>Slash</li></capacities>
							<power>16</power>
							<cooldownTime>1.5</cooldownTime>
							<linkedBodyPartsGroup>FrontRightPaw</linkedBodyPartsGroup>
							<surpriseAttack>
								<extraMeleeDamages>
									<li>
										<def>Stun</def>
										<amount>20</amount>
									</li>
								</extraMeleeDamages>
							</surpriseAttack>
							<armorPenetration>0.45</armorPenetration>
						</li>
						<li Class="CombatExtended.ToolCE">
							<capacities><li>Bite</li></capacities>
							<power>19</power>
							<cooldownTime>2.0</cooldownTime>
							<linkedBodyPartsGroup>Teeth</linkedBodyPartsGroup>
							<surpriseAttack>
								<extraMeleeDamages>
									<li>
										<def>Stun</def>
										<amount>24</amount>
									</li>
								</extraMeleeDamages>
							</surpriseAttack>
							<armorPenetration>1.4</armorPenetration>
						</li>
					</tools>
				</value>
			</li>
		</operations>
	</Operation>
</Patch>













